ctnet/__init__.py
ctnet/infer/__init__.py
ctnet/infer/__main__.py
ctnet/modules/__init__.py
ctnet/modules/ctnet.py
ctnet/trainer/__init__.py
ctnet/trainer/__main__.py
ctnet/trainer/ctnet_trainer.py
ctnet/trainer/functional.py
ctnet-1.0.2.dist-info/METADATA
ctnet-1.0.2.dist-info/WHEEL
ctnet-1.0.2.dist-info/top_level.txt
ctnet-1.0.2.dist-info/RECORD
